README.md
setup.cfg
setup.py
discord/ext/owoify/__init__.py
discord/ext/owoify/errors.py
discord/ext/owoify/useful.py
discord_ext_owoify.egg-info/PKG-INFO
discord_ext_owoify.egg-info/SOURCES.txt
discord_ext_owoify.egg-info/dependency_links.txt
discord_ext_owoify.egg-info/requires.txt
discord_ext_owoify.egg-info/top_level.txt