Metadata-Version: 2.1
Name: discord-ext-owoify
Version: 0.0.6a0
Summary: An extension module to owoify text
Home-page: https://github.com/GreenDiscord/discord-ext-owoify/
Author: Green
License: MIT
Download-URL: https://github.com/GreenDiscord/discord-ext-owoify/archive/v0.0.6-a.tar.gz
Platform: UNKNOWN
Requires-Python: >=3.5.3
